adafruit_simple_text_display.py
adafruit_circuitpython_simple_text_display-1.2.21.dist-info/licenses/LICENSE
adafruit_circuitpython_simple_text_display-1.2.21.dist-info/METADATA
adafruit_circuitpython_simple_text_display-1.2.21.dist-info/WHEEL
adafruit_circuitpython_simple_text_display-1.2.21.dist-info/top_level.txt
adafruit_circuitpython_simple_text_display-1.2.21.dist-info/RECORD
