Metadata-Version: 2.4
Name: adafruit-circuitpython-simple-text-display
Version: 1.2.21
Summary: A helper library for displaying lines of text on a microcontroller with a built-in display, or externally connected display.
Author-email: Adafruit Industries <circuitpython@adafruit.com>
License: MIT
Project-URL: Homepage, https://github.com/adafruit/Adafruit_CircuitPython_Simple_Text_Display.git
Keywords: adafruit,blinka,circuitpython,micropython,simple-text-display,displayio
Classifier: Intended Audience :: Developers
Classifier: Topic :: Software Development :: Libraries
Classifier: Topic :: Software Development :: Embedded Systems
Classifier: Topic :: System :: Hardware
Classifier: License :: OSI Approved :: MIT License
Classifier: Programming Language :: Python :: 3
License-File: LICENSE
Requires-Dist: Adafruit-Blinka
Requires-Dist: adafruit-circuitpython-display-text
Provides-Extra: optional
Dynamic: license-file
